poetrybot/__init__.py
poetrybot/config.py
poetrybot/database/__init__.py
poetrybot/database/api.py
poetrybot/database/models.py
poetrybot/main.py
poetrybot/telegram/__init__.py
poetrybot/telegram/bot.py
poetrybot/telegram/commands/help.py
poetrybot/telegram/commands/quote.py
poetrybot/web/application.py
poetrybot/web/errors.py
poetrybot/web/poems/__init__.py
poetrybot/web/poems/routes.py
poetrybot/web/poems/schemas.py
poetrybot/web/poets/__init__.py
poetrybot/web/poets/routes.py
poetrybot/web/poets/schemas.py
poetrybot/web/users/__init__.py
poetrybot/web/users/routes.py
poetrybot/web/users/schemas.py
poetrybot/web/wsgi.py
poetrybot-0.2.0.dist-info/WHEEL
poetrybot-0.2.0.dist-info/entry_points.txt
poetrybot-0.2.0.dist-info/LICENSE
poetrybot-0.2.0.dist-info/METADATA
poetrybot-0.2.0.dist-info/RECORD
