Metadata-Version: 2.1
Name: poetrybot
Version: 0.2.0
Summary: poetrybot is a Telegram bot to quote poems between friends.
Home-page: https://noa.mornie.org/eriol/poetrybot
Keywords: telegram,bot
Author: Daniele Tricoli
Author-email: eriol@mornie.org
Requires-Python: >=3.9,<4.0
Classifier: Programming Language :: Python :: 3
Classifier: Programming Language :: Python :: 3.9
Classifier: Programming Language :: Python :: 3.10
Classifier: Programming Language :: Python :: 3.11
Requires-Dist: Flask (>=2.2.3,<3.0.0)
Requires-Dist: SQLAlchemy (>=1.4.3,<2.0.0)
Requires-Dist: environ-config (>=23.1.0,<24.0.0)
Requires-Dist: marshmallow (>=3.19.0,<4.0.0)
Requires-Dist: python-telegram-bot (>=20.1,<21.0)
Project-URL: Repository, https://noa.mornie.org/eriol/poetrybot
